setup.py
rqalpha_mod_hello/__init__.py
rqalpha_mod_hello/mod.py
rqalpha_mod_hello_houzhj.egg-info/PKG-INFO
rqalpha_mod_hello_houzhj.egg-info/SOURCES.txt
rqalpha_mod_hello_houzhj.egg-info/dependency_links.txt
rqalpha_mod_hello_houzhj.egg-info/not-zip-safe
rqalpha_mod_hello_houzhj.egg-info/top_level.txt