Metadata-Version: 1.1
Name: rqalpha-mod-hello-houzhj
Version: 0.1.0
Summary: RQAlpha Mod to say hello  houzhj
Home-page: https://github.com/johnsonchak/rqalpha-mod-hello
Author: houzhj
Author-email: houzhj58@163.com
License: Apache License v2
Platform: UNKNOWN
Classifier: Programming Language :: Python
Classifier: Operating System :: Microsoft :: Windows
Classifier: Operating System :: Unix
Classifier: Programming Language :: Python :: 3.5
Classifier: Programming Language :: Python :: 3.6
